{
  "info": {
    "name": "Ticketing Platform API",
    "description": "Collection for testing the ticketing platform microservices via the API gateway.",
    "schema": "https://schema.getpostman.com/json/collection/v2.1.0/collection.json"
  },
  "variable": [
    { "key": "BASE_URL", "value": "http://localhost:8080/api", "type": "string" },
    { "key": "jwt_token", "value": "", "type": "string" }
  ],
  "item": [
    {
      "name": "Auth",
      "item": [
        {
          "name": "Register",
          "request": {
            "method": "POST",
            "header": [
              { "key": "Content-Type", "value": "application/json" }
            ],
            "body": {
              "mode": "raw",
              "raw": "{\\n  \\\"username\\\": \\\"newuser\\\",\\n  \\\"password\\\": \\\"password\\\"\\n}"
            },
            "url": {
              "raw": "{{BASE_URL}}/auth/register",
              "host": ["{{BASE_URL}}"],
              "path": ["auth","register"]
            }
          }
        },
        {
          "name": "Login",
          "event": [
            {
              "listen": "test",
              "script": {
                "type": "text/javascript",
                "exec": [
                  "pm.collectionVariables.set(\"jwt_token\", pm.response.json().token);"
                ]
              }
            }
          ],
          "request": {
            "method": "POST",
            "header": [
              { "key": "Content-Type", "value": "application/json" }
            ],
            "body": {
              "mode": "raw",
              "raw": "{\n  \"username\": \"user\",\n  \"password\": \"password\"\n}"
            },
            "url": {
              "raw": "{{BASE_URL}}/auth/login",
              "host": ["{{BASE_URL}}"],
              "path": ["auth","login"]
            }
          }
        },
        {
          "name": "Me",
          "request": {
            "method": "GET",
            "header": [
              { "key": "Authorization", "value": "Bearer {{jwt_token}}" }
            ],
            "url": {
              "raw": "{{BASE_URL}}/auth/me",
              "host": ["{{BASE_URL}}"],
              "path": ["auth","me"]
            }
          }
        }
      ]
    },
    {
      "name": "Catalog",
      "item": [
        {
          "name": "Get All Events",
          "request": {
            "method": "GET",
            "header": [
              { "key": "Authorization", "value": "Bearer {{jwt_token}}" }
            ],
            "url": {
              "raw": "{{BASE_URL}}/catalog/events",
              "host": ["{{BASE_URL}}"],
              "path": ["catalog","events"],
              "query": [
                {"key": "city", "value": ""},
                {"key": "from", "value": ""},
                {"key": "to", "value": ""},
                {"key": "page", "value": ""},
                {"key": "size", "value": ""}
              ]
            }
          }
        },
        {
          "name": "Get Event By Id",
          "request": {
            "method": "GET",
            "header": [
              { "key": "Authorization", "value": "Bearer {{jwt_token}}" }
            ],
            "url": {
              "raw": "{{BASE_URL}}/catalog/events/1",
              "host": ["{{BASE_URL}}"],
              "path": ["catalog","events","1"]
            }
          }
        },
        {
          "name": "Get Venues",
          "request": {
            "method": "GET",
            "header": [
              { "key": "Authorization", "value": "Bearer {{jwt_token}}" }
            ],
            "url": {
              "raw": "{{BASE_URL}}/catalog/venues",
              "host": ["{{BASE_URL}}"],
              "path": ["catalog","venues"]
            }
          }
        },
        {
          "name": "Get Venue Halls",
          "request": {
            "method": "GET",
            "header": [
              { "key": "Authorization", "value": "Bearer {{jwt_token}}" }
            ],
            "url": {
              "raw": "{{BASE_URL}}/catalog/venues/1/halls",
              "host": ["{{BASE_URL}}"],
              "path": ["catalog","venues","1","halls"]
            }
          }
        }
      ]
    },
    {
      "name": "Inventory",
      "item": [
        {
          "name": "List Seats",
          "request": {
            "method": "GET",
            "header": [
              { "key": "Authorization", "value": "Bearer {{jwt_token}}" }
            ],
            "url": {
              "raw": "{{BASE_URL}}/inventory/seats?eventId=1",
              "host": ["{{BASE_URL}}"],
              "path": ["inventory","seats"],
              "query": [ {"key": "eventId", "value": "1"} ]
            }
          }
        },
        {
          "name": "Lock Seats",
          "request": {
            "method": "POST",
            "header": [
              { "key": "Content-Type", "value": "application/json" },
              { "key": "Authorization", "value": "Bearer {{jwt_token}}" }
            ],
            "body": {
              "mode": "raw",
              "raw": "{\n  \"eventId\": 1,\n  \"seatLabels\": [\"A1\", \"A2\"],\n  \"lockDurationSeconds\": 300,\n  \"bookingRef\": \"BOOK123\",\n  \"lockedByUser\": 1\n}"
            },
            "url": {
              "raw": "{{BASE_URL}}/inventory/seats/lock",
              "host": ["{{BASE_URL}}"],
              "path": ["inventory","seats","lock"]
            }
          }
        },
        {
          "name": "Release Seats",
          "request": {
            "method": "POST",
            "header": [
              { "key": "Content-Type", "value": "application/json" },
              { "key": "Authorization", "value": "Bearer {{jwt_token}}" }
            ],
            "body": {
              "mode": "raw",
              "raw": "{\n  \"eventId\": 1,\n  \"seatLabels\": [\"A1\", \"A2\"]\n}"
            },
            "url": {
              "raw": "{{BASE_URL}}/inventory/seats/release",
              "host": ["{{BASE_URL}}"],
              "path": ["inventory","seats","release"]
            }
          }
        },
        {
          "name": "Sell Seats",
          "request": {
            "method": "POST",
            "header": [
              { "key": "Content-Type", "value": "application/json" },
              { "key": "Authorization", "value": "Bearer {{jwt_token}}" }
            ],
            "body": {
              "mode": "raw",
              "raw": "{\n  \"eventId\": 1,\n  \"seatLabels\": [\"A1\", \"A2\"]\n}"
            },
            "url": {
              "raw": "{{BASE_URL}}/inventory/seats/sell",
              "host": ["{{BASE_URL}}"],
              "path": ["inventory","seats","sell"]
            }
          }
        }
      ]
    },
    {
      "name": "Booking",
      "item": [
        {
          "name": "Start Booking",
          "request": {
            "method": "POST",
            "header": [
              { "key": "Content-Type", "value": "application/json" },
              { "key": "Authorization", "value": "Bearer {{jwt_token}}" }
            ],
            "body": {
              "mode": "raw",
              "raw": "{\n  \"userId\": 1,\n  \"eventId\": 1,\n  \"currency\": \"USD\",\n  \"items\": [\n    {\n      \"seatLabel\": \"A1\",\n      \"tierId\": 1,\n      \"priceAtBooking\": 100.0\n    }\n  ]\n}"
            },
            "url": {
              "raw": "{{BASE_URL}}/booking",
              "host": ["{{BASE_URL}}"],
              "path": ["booking"]
            }
          }
        },
        {
          "name": "Confirm Booking",
          "request": {
            "method": "POST",
            "header": [
              { "key": "Authorization", "value": "Bearer {{jwt_token}}" }
            ],
            "url": {
              "raw": "{{BASE_URL}}/booking/1/confirm",
              "host": ["{{BASE_URL}}"],
              "path": ["booking","1","confirm"]
            }
          }
        },
        {
          "name": "Cancel Booking",
          "request": {
            "method": "POST",
            "header": [
              { "key": "Authorization", "value": "Bearer {{jwt_token}}" }
            ],
            "url": {
              "raw": "{{BASE_URL}}/booking/1/cancel",
              "host": ["{{BASE_URL}}"],
              "path": ["booking","1","cancel"]
            }
          }
        }
      ]
    }
  ]
}
